bug_trail/__about__.py
bug_trail/__init__.py
bug_trail/__main__.py
bug_trail/data_code.py
bug_trail/exceptions.py
bug_trail/fs_utils.py
bug_trail/incremental.py
bug_trail/py.typed
bug_trail/pygments_job.py
bug_trail/view_base.jinja
bug_trail/view_detail.jinja
bug_trail/view_detail.py
bug_trail/view_main.jinja
bug_trail/view_main.py
bug_trail/view_navbar.jinja
bug_trail/view_python_environment.jinja
bug_trail/view_python_environment.py
bug_trail/view_shared.py
bug_trail/view_system_info.jinja
bug_trail/view_system_info.py
bug_trail/views.py
bug_trail/assets/img/logo.png
bug_trail-3.0.0.dist-info/METADATA
bug_trail-3.0.0.dist-info/WHEEL
bug_trail-3.0.0.dist-info/entry_points.txt
bug_trail-3.0.0.dist-info/licenses/LICENSE
bug_trail-3.0.0.dist-info/RECORD
