Metadata-Version: 2.4
Name: bug_trail
Version: 3.0.0
Summary: Local static html error logger to use while developing python code.
Project-URL: Bug Tracker, https://github.com/matthewdeanmartin/bug_trail/issues
Project-URL: Change Log, https://github.com/matthewdeanmartin/bug_trail/blob/main/CHANGES.md
Author-email: Matthew Martin <matthewdeanmartin@gmail.com>
License: MIT
License-File: LICENSE
Keywords: error logging,html log report
Classifier: Development Status :: 4 - Beta
Classifier: Intended Audience :: Developers
Classifier: License :: OSI Approved :: MIT License
Classifier: Operating System :: OS Independent
Classifier: Programming Language :: Python
Classifier: Programming Language :: Python :: 3.11
Requires-Python: >=3.12
Requires-Dist: bug-trail-core==3.1.0
Requires-Dist: humanize
Requires-Dist: jinja2>=3.1.2
Requires-Dist: pygments
Requires-Dist: watchdog>=3.0.0
